setup.py
Topsis_HarshitaPandey_102003235.egg-info/PKG-INFO
Topsis_HarshitaPandey_102003235.egg-info/SOURCES.txt
Topsis_HarshitaPandey_102003235.egg-info/dependency_links.txt
Topsis_HarshitaPandey_102003235.egg-info/requires.txt
Topsis_HarshitaPandey_102003235.egg-info/top_level.txt
topsis/__init__.py
topsis/code.py