Metadata-Version: 2.1
Name: Topsis-HarshitaPandey-102003235
Version: 1.0
Summary: Python implementation of the Technique for Order of Preference by Similarity to Ideal Solution (TOPSIS)
Author: Harshita Pandey
License: UNKNOWN
Platform: UNKNOWN
